opni_nats_test/__init__.py
opni_nats_test/jetstream-example.py
opni_nats_test/nats_wrapper.py
opni_nats_test-0.0.2.0.dist-info/LICENSE
opni_nats_test-0.0.2.0.dist-info/METADATA
opni_nats_test-0.0.2.0.dist-info/WHEEL
opni_nats_test-0.0.2.0.dist-info/top_level.txt
opni_nats_test-0.0.2.0.dist-info/RECORD
